LICENSE
MANIFEST.in
README.md
setup.py
django_nexmo.egg-info/PKG-INFO
django_nexmo.egg-info/SOURCES.txt
django_nexmo.egg-info/dependency_links.txt
django_nexmo.egg-info/top_level.txt
nexmo/__init__.py
nexmo/__init__.pyc
nexmo/error_messages.py
nexmo/models.py
nexmo/urls.py
nexmo/utils.py
nexmo/utils.pyc
nexmo/views.py
nexmo/libpynexmo/README
nexmo/libpynexmo/__init__.py
nexmo/libpynexmo/__init__.pyc
nexmo/libpynexmo/nexmomessage.py
nexmo/libpynexmo/nexmomessage.pyc
nexmo/libpynexmo/nexmosample.py