Metadata-Version: 1.1
Name: django-nexmo
Version: 1.0.0
Summary: A simple Django app to send text messages using the Nexmo api.
Home-page: https://github.com/thibault/django-nexmo
Author: Thibault Jouannic
Author-email: thibault@miximum.fr
License: WTFPL
Platform: UNKNOWN
Classifier: Environment :: Web Environment
Classifier: Framework :: Django
Classifier: Intended Audience :: Developers
Classifier: License :: OSI Approved
Classifier: Operating System :: OS Independent
Classifier: Programming Language :: Python
Classifier: Programming Language :: Python :: 2.7
Classifier: Topic :: Internet :: WWW/HTTP
Classifier: Topic :: Internet :: WWW/HTTP :: Dynamic Content
